<work xmlns="http://chs.harvard.edu/xmlns/cts"
  groupUrn="urn:cts:latinLit:stoa0276"
  urn="urn:cts:latinLit:stoa0276.stoa009"
  xml:lang="lat"
>
    <title xml:lang="eng">Passio Sanctarum Perpetuae et Felicitatis</title>
    <edition 
      workUrn="urn:cts:latinLit:stoa0276.stoa009" 
      urn="urn:cts:latinLit:stoa0276.stoa009.digilibLT-lat1">
        <label xml:lang="lat">Passio Sanctarum Perpetuae et Felicitatis</label>
        <description xml:lang="lat">Edition from DigilibLT dlt000592</description>
    </edition>
</work>