<work xmlns="http://chs.harvard.edu/xmlns/cts"
  groupUrn="urn:cts:latinLit:stoa0366"
  urn="urn:cts:latinLit:stoa0366.stoa001"
  xml:lang="lat"
>
    <title xml:lang="eng">De morte testamentoque Alexandri Magni</title>
    <edition 
      workUrn="urn:cts:latinLit:stoa0366.stoa001" 
      urn="urn:cts:latinLit:stoa0366.stoa001.digilibLT-lat1">
        <label xml:lang="lat">De morte testamentoque Alexandri Magni</label>
        <description xml:lang="lat">Edition from DigilibLT dlt000518</description>
    </edition>
</work>